Workbook

Sheet EmployeeData
A1: EmpID | B1: Name | C1: Department | D1: Role | E1: Monthly Salary (₹) | F1: Attendance % | G1: Dept Budget (₹) [VLOOKUP]
A2: 1001 | B2: Aditi | C2: Sales | D2: Sales Executive | E2: 42952 | F2: 80.3 | G2: =VLOOKUP(C2,DeptBudget!$A$2:$C$6,2,FALSE()) -> 250000
A3: 1002 | B3: Rohan | C3: Sales | D3: Sales Associate | E3: 31012 | F3: 83.1 | G3: =VLOOKUP(C3,DeptBudget!$A$2:$C$6,2,FALSE()) -> 250000
A4: 1003 | B4: Priya | C4: Sales | D4: Sales Executive | E4: 26572 | F4: 93.5 | G4: =VLOOKUP(C4,DeptBudget!$A$2:$C$6,2,FALSE()) -> 250000
A5: 1004 | B5: Karan | C5: Sales | D5: Sales Associate | E5: 44174 | F5: 93.6 | G5: =VLOOKUP(C5,DeptBudget!$A$2:$C$6,2,FALSE()) -> 250000
A6: 1005 | B6: Neha | C6: Sales | D6: Sales Executive | E6: 39870 | F6: 79.8 | G6: =VLOOKUP(C6,DeptBudget!$A$2:$C$6,2,FALSE()) -> 250000
A7: 1006 | B7: Arjun | C7: Sales | D7: Sales Associate | E7: 35825 | F7: 78.7 | G7: =VLOOKUP(C7,DeptBudget!$A$2:$C$6,2,FALSE()) -> 250000
A8: 1007 | B8: Simran | C8: HR | D8: HR Associate | E8: 25070 | F8: 82.6 | G8: =VLOOKUP(C8,DeptBudget!$A$2:$C$6,2,FALSE()) -> 150000
A9: 1008 | B9: Vikram | C9: HR | D9: Recruiter | E9: 38559 | F9: 90.6 | G9: =VLOOKUP(C9,DeptBudget!$A$2:$C$6,2,FALSE()) -> 150000
A10: 1009 | B10: Isha | C10: HR | D10: HR Associate | E10: 40390 | F10: 82.2 | G10: =VLOOKUP(C10,DeptBudget!$A$2:$C$6,2,FALSE()) -> 150000
A11: 1010 | B11: Rahul | C11: HR | D11: Recruiter | E11: 43295 | F11: 92.7 | G11: =VLOOKUP(C11,DeptBudget!$A$2:$C$6,2,FALSE()) -> 150000
A12: 1011 | B12: Pooja | C12: HR | D12: HR Associate | E12: 35746 | F12: 82.6 | G12: =VLOOKUP(C12,DeptBudget!$A$2:$C$6,2,FALSE()) -> 150000
A13: 1012 | B13: Aman | C13: HR | D13: Recruiter | E13: 41309 | F13: 83.8 | G13: =VLOOKUP(C13,DeptBudget!$A$2:$C$6,2,FALSE()) -> 150000
... A31: 1030 | B31: Varun | C31: Marketing | D31: Content Executive | E31: 36857 | F31: 91.3 | G31: =VLOOKUP(C31,DeptBudget!$A$2:$C$6,2,FALSE()) -> 200000

Sheet DeptBudget
A1: Department | B1: Monthly Budget (₹) | C1: Headcount Target | E1: Source: sample assumptions set for this project (not real company data)
A2: Sales | B2: 250000 | C2: 6
A3: HR | B3: 150000 | C3: 6
A4: IT | B4: 280000 | C4: 6
A5: Finance | B5: 180000 | C5: 6
A6: Marketing | B6: 200000 | C6: 6

Sheet QuarterlyTargets
A1: Metric | B1: Sales | C1: HR | D1: IT | E1: Finance | F1: Marketing
A2: Revenue Target (₹L) | B2: 18 | C2: 4 | D2: 12 | E2: 6 | F2: 9
A3: Headcount Target | B3: 6 | C3: 6 | D3: 6 | E3: 6 | F3: 6

Sheet MIS Summary
A1: Monthly MIS Report — Department Summary
A3: Department | B3: Headcount | C3: Total Salary (₹) | D3: Avg Attendance % | E3: Revenue Target (₹L) [HLOOKUP]
A4: Sales | B4: =COUNTIF(EmployeeData!$C$2:$C$31,A4) -> 6 | C4: =SUMIF(EmployeeData!$C$2:$C$31,A4,EmployeeData!$E$2:$E$31) -> 220405 | D4: =ROUND(AVERAGEIF(EmployeeData!$C$2:$C$31,A4,EmployeeData!$F$2:$F$31),1) -> 84.8 | E4: =HLOOKUP(A4,QuarterlyTargets!$B$1:$F$3,2,FALSE()) -> 18
A5: HR | B5: =COUNTIF(EmployeeData!$C$2:$C$31,A5) -> 6 | C5: =SUMIF(EmployeeData!$C$2:$C$31,A5,EmployeeData!$E$2:$E$31) -> 224369 | D5: =ROUND(AVERAGEIF(EmployeeData!$C$2:$C$31,A5,EmployeeData!$F$2:$F$31),1) -> 85.8 | E5: =HLOOKUP(A5,QuarterlyTargets!$B$1:$F$3,2,FALSE()) -> 4
A6: IT | B6: =COUNTIF(EmployeeData!$C$2:$C$31,A6) -> 6 | C6: =SUMIF(EmployeeData!$C$2:$C$31,A6,EmployeeData!$E$2:$E$31) -> 179125 | D6: =ROUND(AVERAGEIF(EmployeeData!$C$2:$C$31,A6,EmployeeData!$F$2:$F$31),1) -> 88.1 | E6: =HLOOKUP(A6,QuarterlyTargets!$B$1:$F$3,2,FALSE()) -> 12
A7: Finance | B7: =COUNTIF(EmployeeData!$C$2:$C$31,A7) -> 6 | C7: =SUMIF(EmployeeData!$C$2:$C$31,A7,EmployeeData!$E$2:$E$31) -> 204540 | D7: =ROUND(AVERAGEIF(EmployeeData!$C$2:$C$31,A7,EmployeeData!$F$2:$F$31),1) -> 89.4 | E7: =HLOOKUP(A7,QuarterlyTargets!$B$1:$F$3,2,FALSE()) -> 6
A8: Marketing | B8: =COUNTIF(EmployeeData!$C$2:$C$31,A8) -> 6 | C8: =SUMIF(EmployeeData!$C$2:$C$31,A8,EmployeeData!$E$2:$E$31) -> 174376 | D8: =ROUND(AVERAGEIF(EmployeeData!$C$2:$C$31,A8,EmployeeData!$F$2:$F$31),1) -> 89.4 | E8: =HLOOKUP(A8,QuarterlyTargets!$B$1:$F$3,2,FALSE()) -> 9
A10: Note: figures are sample data built for this practice project, not real company records.

Sheet Pivot Analysis
A3: Department | B3: Sum of monthly salary | C3: Average of Attendance %
A4: Finance | B4: 204540 | C4: 89.383333
A5: HR | B5: 224369 | C5: 85.75
A6: IT | B6: 179125 | C6: 88.1
A7: Marketing | B7: 174376 | C7: 89.433333
A8: Sales | B8: 220405 | C8: 84.833333
A9: Grand Total | B9: 1002815 | C9: 87.5
